{
	"system" : {
		"platform" : "windows64",
		"os_name" : "Windows 10",
		"os_version" : "10.0"
	},
	"error" : {
		"executable" : "quartus",
		"comment" : "not_applicable",
		"error_message" : "Access Violation at 0X00007FFE28E2D600",
		"source_file" : "unknown",
		"line" : "0",
		"stack_trace" : "\t0x7ffe28e2d5ff: db_vdb + 0x2d5ff (?set_run@VDB_COMMENT@@QEAAXH@Z + 0x3)\n\t0x7ffdff3cb4fb: edt_wedtq + 0x4b4fb (?rearrange_rows@WEDTQ_NODE_VIEW@@QEAAXHV?$QList@H@@@Z + 0x62b)\n\t0x7ffdff3c8175: edt_wedtq + 0x48175 (?dropEvent@WEDTQ_NODE_VIEW@@MEAAXPEAVQDropEvent@@@Z + 0x1d5)\n\t 0x505b2082: QtGui4 + 0x62082 (?event@QWidget@@MEAA_NPEAVQEvent@@@Z + 0x5d2)\n\t 0x508d7126: QtGui4 + 0x387126 (?event@QFrame@@MEAA_NPEAVQEvent@@@Z + 0x36)\n\t 0x509ca44c: QtGui4 + 0x47a44c (?viewportEvent@QAbstractItemView@@MEAA_NPEAVQEvent@@@Z + 0x4ac)\n\t0x7ffe518c4d76: GCL_AFCQ + 0xb4d76 (?viewportEvent@AFCQ_TREE_VIEW@@MEAA_NPEAVQEvent@@@Z + 0x2b6)\n\t 0x50370b22: QtCore4 + 0x110b22 (?sendThroughObjectEventFilters@QCoreApplicationPrivate@@QEAA_NPEAVQObject@@PEAVQEvent@@@Z + 0x82)\n\t 0x50572c41: QtGui4 + 0x22c41 (?notify_helper@QApplicationPrivate@@QEAA_NPEAVQObject@@PEAVQEvent@@@Z + 0xe1)\n\t 0x505720bd: QtGui4 + 0x220bd (?notify@QApplication@@UEAA_NPEAVQObject@@PEAVQEvent@@@Z + 0xf8d)\n\t 0x5036ec4b: QtCore4 + 0x10ec4b (?notifyInternal@QCoreApplication@@AEAA_NPEAVQObject@@PEAVQEvent@@@Z + 0x7b)\n\t 0x505dd7f3: QtGui4 + 0x8d7f3 (?screenNumber@QDesktopWidget@@QEBAHPEBVQWidget@@@Z + 0xc73)\n\t0x7ffe92fabae7: ole32 + 0xcbae7 (RevokeActiveObjectExt + 0xcef7)\n\t0x7ffe92fab98b: ole32 + 0xcb98b (RevokeActiveObjectExt + 0xcd9b)\n\t0x7ffe92f69178: ole32 + 0x89178 (OleGetPackageClipboardOwner + 0x9f88)\n\t0x7ffe92f68864: ole32 + 0x88864 (OleGetPackageClipboardOwner + 0x9674)\n\t0x7ffe92f6c937: ole32 + 0x8c937 (DoDragDrop + 0x127)\n\t 0x505deacd: QtGui4 + 0x8eacd (?accept@QDragMoveEvent@@QEAAXXZ + 0xacd)\n\t 0x5058045f: QtGui4 + 0x3045f (?exec@QDrag@@QEAA?AW4DropAction@Qt@@V?$QFlags@W4DropAction@Qt@@@@W423@@Z + 0x9f)\n\t 0x505803b6: QtGui4 + 0x303b6 (?exec@QDrag@@QEAA?AW4DropAction@Qt@@V?$QFlags@W4DropAction@Qt@@@@@Z + 0x16)\n\t0x7ffdff3c9b25: edt_wedtq + 0x49b25 (?mouseMoveEvent@WEDTQ_NODE_VIEW@@MEAAXPEAVQMouseEvent@@@Z + 0x245)\n\t 0x505b1b5f: QtGui4 + 0x61b5f (?event@QWidget@@MEAA_NPEAVQEvent@@@Z + 0xaf)\n\t 0x508d7126: QtGui4 + 0x387126 (?event@QFrame@@MEAA_NPEAVQEvent@@@Z + 0x36)\n\t 0x509ca44c: QtGui4 + 0x47a44c (?viewportEvent@QAbstractItemView@@MEAA_NPEAVQEvent@@@Z + 0x4ac)\n\t0x7ffe518c4d76: GCL_AFCQ + 0xb4d76 (?viewportEvent@AFCQ_TREE_VIEW@@MEAA_NPEAVQEvent@@@Z + 0x2b6)\n\t 0x50370b22: QtCore4 + 0x110b22 (?sendThroughObjectEventFilters@QCoreApplicationPrivate@@QEAA_NPEAVQObject@@PEAVQEvent@@@Z + 0x82)\n\t 0x50572c41: QtGui4 + 0x22c41 (?notify_helper@QApplicationPrivate@@QEAA_NPEAVQObject@@PEAVQEvent@@@Z + 0xe1)\n\t 0x5057184e: QtGui4 + 0x2184e (?notify@QApplication@@UEAA_NPEAVQObject@@PEAVQEvent@@@Z + 0x71e)\n\t 0x5036ec4b: QtCore4 + 0x10ec4b (?notifyInternal@QCoreApplication@@AEAA_NPEAVQObject@@PEAVQEvent@@@Z + 0x7b)\n\t 0x50575a9e: QtGui4 + 0x25a9e (?sendMouseEvent@QApplicationPrivate@@SA_NPEAVQWidget@@PEAVQMouseEvent@@00PEAPEAV2@AEAV?$QPointer@VQWidget@@@@_N@Z + 0x1de)\n\t 0x505d6940: QtGui4 + 0x86940 (?trUtf8@QScrollBar@@SA?AVQString@@PEBD0H@Z + 0x1440)\n\t 0x505da301: QtGui4 + 0x8a301 (?winMouseButtonUp@QApplication@@SAXXZ + 0x2761)\n\t0x7ffe936fe7e7: USER32 + 0xe7e7 (CallWindowProcW + 0x3f7)\n\t0x7ffe936fe228: USER32 + 0xe228 (DispatchMessageW + 0x258)\n\t 0x50393982: QtCore4 + 0x133982 (?processEvents@QEventDispatcherWin32@@UEAA_NV?$QFlags@W4ProcessEventsFlag@QEventLoop@@@@@Z + 0x3e2)\n\t 0x505d2004: QtGui4 + 0x82004 (?openPopup@QApplicationPrivate@@QEAAXPEAVQWidget@@@Z + 0x204)\n\t 0x5036bb7b: QtCore4 + 0x10bb7b (?exec@QEventLoop@@QEAAHV?$QFlags@W4ProcessEventsFlag@QEventLoop@@@@@Z + 0x22b)\n\t 0x5036e18f: QtCore4 + 0x10e18f (?exec@QCoreApplication@@SAHXZ + 0xdf)\n\t0x7ff68ac8198b: quartus + 0x198b (?qgq_main@@YAHHPEAPEBD@Z + 0x8b)\n\t0x7ffe7aef3258: CCL_MSG + 0x13258 (?msg_main_thread@@YAPEAXPEAX@Z + 0x18)\n\t0x7ffe7aef4a5e: CCL_MSG + 0x14a5e (?msg_thread_wrapper@@YAPEAXP6APEAXPEAX@Z0@Z + 0x6e)\n\t0x7ffe7aeb6af0: ccl_mem + 0x16af0 (?mem_thread_wrapper@@YAPEAXP6APEAXPEAX@Z0@Z + 0x70)\n\t0x7ffe7aef2af1: CCL_MSG + 0x12af1 (?msg_exe_main@@YAHHPEAPEBDP6AHH0@Z@Z + 0xa1)\n\t0x7ff68ac82777: quartus + 0x2777 (WinMain + 0x127)\n\t0x7ff68ac81f40: quartus + 0x1f40 (__tmainCRTStartup + 0x148)\n\t0x7ffe93ad7033: KERNEL32 + 0x17033 (BaseThreadInitThunk + 0x13)\n\t0x7ffe93e82650: ntdll + 0x52650 (RtlUserThreadStart + 0x20)\n",
		"subsystem" : "unknown"
	},
	"quartus" : {
		"quartus_bits" : "64",
		"version" : "20.1.0",
		"build" : "711",
		"edition" : "Lite Edition"
	}
}